imagecaptioning/__init__.py
imagecaptioning/caption.py
imagecaptioning/create_input_files.py
imagecaptioning/definitions.py
imagecaptioning/train.py
imagecaptioning/utils.py
imagecaptioning/data/__init__.py
imagecaptioning/data/datasets.py
imagecaptioning/data/make_dataset.py
imagecaptioning/features/__init__.py
imagecaptioning/features/build_features.py
imagecaptioning/models/__init__.py
imagecaptioning/models/caption.py
imagecaptioning/models/eval.py
imagecaptioning/models/models.py
imagecaptioning/visualization/__init__.py
imagecaptioning/visualization/visualize.py
src/__init__.py
src/caption.py
src/create_input_files.py
src/definitions.py
src/train.py
src/utils.py
src/data/__init__.py
src/data/datasets.py
src/data/make_dataset.py
src/features/__init__.py
src/features/build_features.py
src/models/__init__.py
src/models/caption.py
src/models/eval.py
src/models/models.py
src/visualization/__init__.py
src/visualization/visualize.py
imagecaptioning_aeye-0.1.6.dist-info/LICENSE
imagecaptioning_aeye-0.1.6.dist-info/METADATA
imagecaptioning_aeye-0.1.6.dist-info/WHEEL
imagecaptioning_aeye-0.1.6.dist-info/top_level.txt
imagecaptioning_aeye-0.1.6.dist-info/RECORD
