Metadata-Version: 2.1
Name: imagecaptioning-aeye
Version: 0.1.6
Summary: The Image Captioning module for the A-eye project.
Home-page: https://github.com/jjmachan/imagecaptioning-aeye
Author: jjmachan
License: MIT
Platform: UNKNOWN
Classifier: Programming Language :: Python :: 3
Classifier: License :: OSI Approved :: MIT License
Classifier: Operating System :: OS Independent
Requires-Python: >=3.6
